{
  "pagination": {
    "GetAnomalies": {
      "input_token": "NextPageToken",
      "output_token": "NextPageToken",
      "limit_key": "MaxResults",
      "result_key": "Anomalies"
    },
    "GetAnomalyMonitors": {
      "input_token": "NextPageToken",
      "output_token": "NextPageToken",
      "limit_key": "MaxResults",
      "result_key": "AnomalyMonitors"
    },
    "GetAnomalySubscriptions": {
      "input_token": "NextPageToken",
      "output_token": "NextPageToken",
      "limit_key": "MaxResults",
      "result_key": "AnomalySubscriptions"
    }
  }
}
