[
  {
    "category": "``iot``",
    "description": "Added Create/Update/Delete/Describe/List APIs for a new IoT resource named FleetMetric. Added a new Fleet Indexing query API named GetBucketsAggregation. Added a new field named DisconnectedReason in Fleet Indexing query response. Updated their related documentations.",
    "type": "api-change"
  },
  {
    "category": "``compute-optimizer``",
    "description": "Documentation updates for Compute Optimizer",
    "type": "api-change"
  },
  {
    "category": "``sqs``",
    "description": "Amazon SQS adds a new queue attribute, RedriveAllowPolicy, which includes the dead-letter queue redrive permission parameters. It defines which source queues can specify dead-letter queues as a JSON object.",
    "type": "api-change"
  },
  {
    "category": "``memorydb``",
    "description": "Documentation updates for MemoryDB",
    "type": "api-change"
  },
  {
    "category": "``polly``",
    "description": "Amazon Polly adds new South African English voice - Ayanda. Ayanda is available as Neural voice only.",
    "type": "api-change"
  }
]