[
  {
    "category": "``iotfleetwise``",
    "description": "Deprecated assignedValue property for actuators and attributes.  Added a message to invalid nodes and invalid decoder manifest exceptions.",
    "type": "api-change"
  },
  {
    "category": "``logs``",
    "description": "Doc-only update for CloudWatch Logs, for Tagging Permissions clarifications",
    "type": "api-change"
  },
  {
    "category": "``medialive``",
    "description": "Link devices now support buffer size (latency) configuration. A higher latency value means a longer delay in transmitting from the device to MediaLive, but improved resiliency. A lower latency value means a shorter delay, but less resiliency.",
    "type": "api-change"
  },
  {
    "category": "``mediapackage-vod``",
    "description": "This release provides the approximate number of assets in a packaging group.",
    "type": "api-change"
  }
]