[
  {
    "category": "``clouddirectory``",
    "description": "Enabled FIPS endpoints for GovCloud (US) regions in SDK.",
    "type": "api-change"
  },
  {
    "category": "``cloudformation``",
    "description": "This feature provides a method of obtaining which regions a stackset has stack instances deployed in.",
    "type": "api-change"
  },
  {
    "category": "``discovery``",
    "description": "Update ImportName validation to 255 from the current length of 100",
    "type": "api-change"
  },
  {
    "category": "``dlm``",
    "description": "Enabled FIPS endpoints for GovCloud (US) regions in SDK.",
    "type": "api-change"
  },
  {
    "category": "``ec2``",
    "description": "We add Prefix Lists as a new route destination option for LocalGatewayRoutes. This will allow customers to create routes to Prefix Lists. Prefix List routes will allow customers to group individual CIDR routes with the same target into a single route.",
    "type": "api-change"
  },
  {
    "category": "``imagebuilder``",
    "description": "Enabled FIPS endpoints for GovCloud (US) regions in SDK.",
    "type": "api-change"
  },
  {
    "category": "``kafka``",
    "description": "Enabled FIPS endpoints for GovCloud (US) regions in SDK.",
    "type": "api-change"
  },
  {
    "category": "``mediaconvert``",
    "description": "Enabled FIPS endpoints for GovCloud (US) regions in SDK.",
    "type": "api-change"
  },
  {
    "category": "``swf``",
    "description": "Enabled FIPS endpoints for GovCloud (US) regions in SDK.",
    "type": "api-change"
  }
]