[
  {
    "category": "``connect``",
    "description": "Supervisor Barge for Chat is now supported through the MonitorContact API.",
    "type": "api-change"
  },
  {
    "category": "``connectparticipant``",
    "description": "Introduce new Supervisor participant role",
    "type": "api-change"
  },
  {
    "category": "``location``",
    "description": "Location SDK documentation update. Added missing fonts to the MapConfiguration data type. Updated note for the SubMunicipality property in the place data type.",
    "type": "api-change"
  },
  {
    "category": "``mwaa``",
    "description": "This Amazon MWAA feature release includes new fields in CreateWebLoginToken response model. The new fields IamIdentity and AirflowIdentity will let you match identifications, as the Airflow identity length is currently hashed to 64 characters.",
    "type": "api-change"
  },
  {
    "category": "``s3control``",
    "description": "S3 On Outposts team adds dualstack endpoints support for S3Control and S3Outposts API calls.",
    "type": "api-change"
  },
  {
    "category": "``supplychain``",
    "description": "This release includes APIs CreateBillOfMaterialsImportJob and GetBillOfMaterialsImportJob.",
    "type": "api-change"
  },
  {
    "category": "``transfer``",
    "description": "AWS Transfer Family now supports static IP addresses for SFTP & AS2 connectors and for async MDNs on AS2 servers.",
    "type": "api-change"
  },
  {
    "category": "``endpoint-rules``",
    "description": "Update endpoint-rules command to latest version",
    "type": "api-change"
  }
]