{
  "version": "1.0",
  "resources": {
    "Detector": {
      "operation": "ListDetectors",
      "resourceIdentifier": {
        "DetectorIds": "DetectorIds[]"
      }
    },
    "Filter": {
      "operation": "ListFilters",
      "resourceIdentifier": {
        "FilterNames": "FilterNames[]"
      },
      "inputParameters": [
        "DetectorId"
      ]
    },
    "Finding": {
      "operation": "ListFindings",
      "resourceIdentifier": {
        "FindingIds": "FindingIds[]"
      },
      "inputParameters": [
        "DetectorId"
      ]
    },
    "IPSet": {
      "operation": "ListIPSets",
      "resourceIdentifier": {
        "IpSetIds": "IpSetIds[]"
      },
      "inputParameters": [
        "DetectorId"
      ]
    },
    "Invitation": {
      "operation": "ListInvitations",
      "resourceIdentifier": {
        "InvitationId": "Invitations[].InvitationId"
      }
    },
    "Member": {
      "operation": "ListMembers",
      "resourceIdentifier": {
        "MasterId": "Members[].MasterId"
      },
      "inputParameters": [
        "DetectorId"
      ]
    },
    "ThreatIntelSet": {
      "operation": "ListThreatIntelSets",
      "resourceIdentifier": {
        "ThreatIntelSetIds": "ThreatIntelSetIds[]"
      },
      "inputParameters": [
        "DetectorId"
      ]
    }
  },
  "operations": {
    "AcceptInvitation": {
      "DetectorId": {
        "completions": [
          {
            "parameters": {},
            "resourceName": "Detector",
            "resourceIdentifier": "DetectorId"
          }
        ]
      },
      "InvitationId": {
        "completions": [
          {
            "parameters": {},
            "resourceName": "Invitation",
            "resourceIdentifier": "InvitationId"
          }
        ]
      }
    },
    "ArchiveFindings": {
      "DetectorId": {
        "completions": [
          {
            "parameters": {},
            "resourceName": "Detector",
            "resourceIdentifier": "DetectorId"
          }
        ]
      }
    },
    "CreateFilter": {
      "DetectorId": {
        "completions": [
          {
            "parameters": {},
            "resourceName": "Detector",
            "resourceIdentifier": "DetectorId"
          }
        ]
      }
    },
    "CreateIPSet": {
      "DetectorId": {
        "completions": [
          {
            "parameters": {},
            "resourceName": "Detector",
            "resourceIdentifier": "DetectorId"
          }
        ]
      }
    },
    "CreateMembers": {
      "DetectorId": {
        "completions": [
          {
            "parameters": {},
            "resourceName": "Detector",
            "resourceIdentifier": "DetectorId"
          }
        ]
      }
    },
    "CreateSampleFindings": {
      "DetectorId": {
        "completions": [
          {
            "parameters": {},
            "resourceName": "Detector",
            "resourceIdentifier": "DetectorId"
          }
        ]
      }
    },
    "CreateThreatIntelSet": {
      "DetectorId": {
        "completions": [
          {
            "parameters": {},
            "resourceName": "Detector",
            "resourceIdentifier": "DetectorId"
          }
        ]
      }
    },
    "DeleteDetector": {
      "DetectorId": {
        "completions": [
          {
            "parameters": {},
            "resourceName": "Detector",
            "resourceIdentifier": "DetectorId"
          }
        ]
      }
    },
    "DeleteFilter": {
      "DetectorId": {
        "completions": [
          {
            "parameters": {},
            "resourceName": "Detector",
            "resourceIdentifier": "DetectorId"
          }
        ]
      }
    },
    "DeleteIPSet": {
      "DetectorId": {
        "completions": [
          {
            "parameters": {},
            "resourceName": "Detector",
            "resourceIdentifier": "DetectorId"
          }
        ]
      }
    },
    "DeleteMembers": {
      "DetectorId": {
        "completions": [
          {
            "parameters": {},
            "resourceName": "Detector",
            "resourceIdentifier": "DetectorId"
          }
        ]
      }
    },
    "DeleteThreatIntelSet": {
      "DetectorId": {
        "completions": [
          {
            "parameters": {},
            "resourceName": "Detector",
            "resourceIdentifier": "DetectorId"
          }
        ]
      }
    },
    "DisassociateFromMasterAccount": {
      "DetectorId": {
        "completions": [
          {
            "parameters": {},
            "resourceName": "Detector",
            "resourceIdentifier": "DetectorId"
          }
        ]
      }
    },
    "DisassociateMembers": {
      "DetectorId": {
        "completions": [
          {
            "parameters": {},
            "resourceName": "Detector",
            "resourceIdentifier": "DetectorId"
          }
        ]
      }
    },
    "GetDetector": {
      "DetectorId": {
        "completions": [
          {
            "parameters": {},
            "resourceName": "Detector",
            "resourceIdentifier": "DetectorId"
          }
        ]
      }
    },
    "GetFilter": {
      "DetectorId": {
        "completions": [
          {
            "parameters": {},
            "resourceName": "Detector",
            "resourceIdentifier": "DetectorId"
          }
        ]
      }
    },
    "GetFindings": {
      "DetectorId": {
        "completions": [
          {
            "parameters": {},
            "resourceName": "Detector",
            "resourceIdentifier": "DetectorId"
          }
        ]
      }
    },
    "GetFindingsStatistics": {
      "DetectorId": {
        "completions": [
          {
            "parameters": {},
            "resourceName": "Detector",
            "resourceIdentifier": "DetectorId"
          }
        ]
      }
    },
    "GetIPSet": {
      "DetectorId": {
        "completions": [
          {
            "parameters": {},
            "resourceName": "Detector",
            "resourceIdentifier": "DetectorId"
          }
        ]
      }
    },
    "GetMasterAccount": {
      "DetectorId": {
        "completions": [
          {
            "parameters": {},
            "resourceName": "Detector",
            "resourceIdentifier": "DetectorId"
          }
        ]
      }
    },
    "GetMembers": {
      "DetectorId": {
        "completions": [
          {
            "parameters": {},
            "resourceName": "Detector",
            "resourceIdentifier": "DetectorId"
          }
        ]
      }
    },
    "GetThreatIntelSet": {
      "DetectorId": {
        "completions": [
          {
            "parameters": {},
            "resourceName": "Detector",
            "resourceIdentifier": "DetectorId"
          }
        ]
      }
    },
    "InviteMembers": {
      "DetectorId": {
        "completions": [
          {
            "parameters": {},
            "resourceName": "Detector",
            "resourceIdentifier": "DetectorId"
          }
        ]
      }
    },
    "StartMonitoringMembers": {
      "DetectorId": {
        "completions": [
          {
            "parameters": {},
            "resourceName": "Detector",
            "resourceIdentifier": "DetectorId"
          }
        ]
      }
    },
    "StopMonitoringMembers": {
      "DetectorId": {
        "completions": [
          {
            "parameters": {},
            "resourceName": "Detector",
            "resourceIdentifier": "DetectorId"
          }
        ]
      }
    },
    "UnarchiveFindings": {
      "DetectorId": {
        "completions": [
          {
            "parameters": {},
            "resourceName": "Detector",
            "resourceIdentifier": "DetectorId"
          }
        ]
      }
    },
    "UpdateDetector": {
      "DetectorId": {
        "completions": [
          {
            "parameters": {},
            "resourceName": "Detector",
            "resourceIdentifier": "DetectorId"
          }
        ]
      }
    },
    "UpdateFilter": {
      "DetectorId": {
        "completions": [
          {
            "parameters": {},
            "resourceName": "Detector",
            "resourceIdentifier": "DetectorId"
          }
        ]
      }
    },
    "UpdateFindingsFeedback": {
      "DetectorId": {
        "completions": [
          {
            "parameters": {},
            "resourceName": "Detector",
            "resourceIdentifier": "DetectorId"
          }
        ]
      }
    },
    "UpdateIPSet": {
      "DetectorId": {
        "completions": [
          {
            "parameters": {},
            "resourceName": "Detector",
            "resourceIdentifier": "DetectorId"
          }
        ]
      }
    },
    "UpdateThreatIntelSet": {
      "DetectorId": {
        "completions": [
          {
            "parameters": {},
            "resourceName": "Detector",
            "resourceIdentifier": "DetectorId"
          }
        ]
      }
    }
  }
}
