{
  "version": "1.0",
  "resources": {
    "PolicyStore": {
      "operation": "ListPolicyStores",
      "resourceIdentifier": {
        "policyStoreId": "policyStores[].policyStoreId"
      }
    }
  },
  "operations": {
    "BatchIsAuthorized": {
      "policyStoreId": {
        "completions": [
          {
            "parameters": {},
            "resourceName": "PolicyStore",
            "resourceIdentifier": "policyStoreId"
          }
        ]
      }
    },
    "BatchIsAuthorizedWithToken": {
      "policyStoreId": {
        "completions": [
          {
            "parameters": {},
            "resourceName": "PolicyStore",
            "resourceIdentifier": "policyStoreId"
          }
        ]
      }
    },
    "CreateIdentitySource": {
      "policyStoreId": {
        "completions": [
          {
            "parameters": {},
            "resourceName": "PolicyStore",
            "resourceIdentifier": "policyStoreId"
          }
        ]
      }
    },
    "CreatePolicy": {
      "policyStoreId": {
        "completions": [
          {
            "parameters": {},
            "resourceName": "PolicyStore",
            "resourceIdentifier": "policyStoreId"
          }
        ]
      }
    },
    "CreatePolicyTemplate": {
      "policyStoreId": {
        "completions": [
          {
            "parameters": {},
            "resourceName": "PolicyStore",
            "resourceIdentifier": "policyStoreId"
          }
        ]
      }
    },
    "DeleteIdentitySource": {
      "policyStoreId": {
        "completions": [
          {
            "parameters": {},
            "resourceName": "PolicyStore",
            "resourceIdentifier": "policyStoreId"
          }
        ]
      }
    },
    "DeletePolicy": {
      "policyStoreId": {
        "completions": [
          {
            "parameters": {},
            "resourceName": "PolicyStore",
            "resourceIdentifier": "policyStoreId"
          }
        ]
      }
    },
    "DeletePolicyStore": {
      "policyStoreId": {
        "completions": [
          {
            "parameters": {},
            "resourceName": "PolicyStore",
            "resourceIdentifier": "policyStoreId"
          }
        ]
      }
    },
    "DeletePolicyTemplate": {
      "policyStoreId": {
        "completions": [
          {
            "parameters": {},
            "resourceName": "PolicyStore",
            "resourceIdentifier": "policyStoreId"
          }
        ]
      }
    },
    "GetIdentitySource": {
      "policyStoreId": {
        "completions": [
          {
            "parameters": {},
            "resourceName": "PolicyStore",
            "resourceIdentifier": "policyStoreId"
          }
        ]
      }
    },
    "GetPolicy": {
      "policyStoreId": {
        "completions": [
          {
            "parameters": {},
            "resourceName": "PolicyStore",
            "resourceIdentifier": "policyStoreId"
          }
        ]
      }
    },
    "GetPolicyStore": {
      "policyStoreId": {
        "completions": [
          {
            "parameters": {},
            "resourceName": "PolicyStore",
            "resourceIdentifier": "policyStoreId"
          }
        ]
      }
    },
    "GetPolicyTemplate": {
      "policyStoreId": {
        "completions": [
          {
            "parameters": {},
            "resourceName": "PolicyStore",
            "resourceIdentifier": "policyStoreId"
          }
        ]
      }
    },
    "GetSchema": {
      "policyStoreId": {
        "completions": [
          {
            "parameters": {},
            "resourceName": "PolicyStore",
            "resourceIdentifier": "policyStoreId"
          }
        ]
      }
    },
    "IsAuthorized": {
      "policyStoreId": {
        "completions": [
          {
            "parameters": {},
            "resourceName": "PolicyStore",
            "resourceIdentifier": "policyStoreId"
          }
        ]
      }
    },
    "IsAuthorizedWithToken": {
      "policyStoreId": {
        "completions": [
          {
            "parameters": {},
            "resourceName": "PolicyStore",
            "resourceIdentifier": "policyStoreId"
          }
        ]
      }
    },
    "ListIdentitySources": {
      "policyStoreId": {
        "completions": [
          {
            "parameters": {},
            "resourceName": "PolicyStore",
            "resourceIdentifier": "policyStoreId"
          }
        ]
      }
    },
    "ListPolicies": {
      "policyStoreId": {
        "completions": [
          {
            "parameters": {},
            "resourceName": "PolicyStore",
            "resourceIdentifier": "policyStoreId"
          }
        ]
      }
    },
    "ListPolicyTemplates": {
      "policyStoreId": {
        "completions": [
          {
            "parameters": {},
            "resourceName": "PolicyStore",
            "resourceIdentifier": "policyStoreId"
          }
        ]
      }
    },
    "PutSchema": {
      "policyStoreId": {
        "completions": [
          {
            "parameters": {},
            "resourceName": "PolicyStore",
            "resourceIdentifier": "policyStoreId"
          }
        ]
      }
    },
    "UpdateIdentitySource": {
      "policyStoreId": {
        "completions": [
          {
            "parameters": {},
            "resourceName": "PolicyStore",
            "resourceIdentifier": "policyStoreId"
          }
        ]
      }
    },
    "UpdatePolicy": {
      "policyStoreId": {
        "completions": [
          {
            "parameters": {},
            "resourceName": "PolicyStore",
            "resourceIdentifier": "policyStoreId"
          }
        ]
      }
    },
    "UpdatePolicyStore": {
      "policyStoreId": {
        "completions": [
          {
            "parameters": {},
            "resourceName": "PolicyStore",
            "resourceIdentifier": "policyStoreId"
          }
        ]
      }
    },
    "UpdatePolicyTemplate": {
      "policyStoreId": {
        "completions": [
          {
            "parameters": {},
            "resourceName": "PolicyStore",
            "resourceIdentifier": "policyStoreId"
          }
        ]
      }
    }
  }
}
